aryadocr/__init__.py
aryadocr/aryadcnn.py
aryadocr/context_encoder.py
aryadocr/dataset.py
aryadocr/metrics.py
aryadocr/model.py
aryadocr/processing.py
aryadocr/utils.py
aryadocr-0.1.24.dist-info/METADATA
aryadocr-0.1.24.dist-info/WHEEL
aryadocr-0.1.24.dist-info/top_level.txt
aryadocr-0.1.24.dist-info/RECORD
