Metadata-Version: 2.4
Name: aryadocr
Version: 0.1.24
Summary: Un package Python pour l'OCR 
Author-email: chantry Olanda-Eyiba <chantryolanda85@gmail.com>
License-Expression: MIT
Requires-Dist: matplotlib
Requires-Dist: editdistance
Requires-Dist: tqdm
Requires-Dist: numpy
Requires-Dist: opencv-python
Requires-Dist: torch
Requires-Dist: datasets
Requires-Dist: huggingface-hub
Requires-Dist: tensorflow
